chromaforge/__init__.py
chromaforge/colors.py
chromaforge/components.py
chromaforge/core.py
chromaforge/effects.py
chromaforge/gradient.py
chromaforge/styles.py
chromaforge/terminal.py
chromaforge/themes.py
chromaforge-1.0.1.dist-info/licenses/LICENSE
chromaforge-1.0.1.dist-info/METADATA
chromaforge-1.0.1.dist-info/WHEEL
chromaforge-1.0.1.dist-info/top_level.txt
chromaforge-1.0.1.dist-info/RECORD
