Metadata-Version: 2.4
Name: chromaforge
Version: 1.0.1
Summary: Advanced terminal coloring library for Python - Beyond colorama and rich
Home-page: https://github.com/AeonLtd/chromaforge
Author: PyIDE Team
Author-email: PyIDE Team <support@pyide.org>
Maintainer-email: PyIDE Team <support@pyide.org>
License: MIT
Project-URL: Homepage, https://github.com/AeonLtd/chromaforge
Project-URL: Documentation, https://github.com/AeonLtd/chromaforge#readme
Project-URL: Repository, https://github.com/AeonLtd/chromaforge.git
Project-URL: Issues, https://github.com/AeonLtd/chromaforge/issues
Keywords: terminal,color,ansi,console,cli,styling,gradient,rgb,truecolor,formatting
Classifier: Development Status :: 5 - Production/Stable
Classifier: Environment :: Console
Classifier: Intended Audience :: Developers
Classifier: Operating System :: OS Independent
Classifier: Programming Language :: Python :: 3
Classifier: Programming Language :: Python :: 3.8
Classifier: Programming Language :: Python :: 3.9
Classifier: Programming Language :: Python :: 3.10
Classifier: Programming Language :: Python :: 3.11
Classifier: Programming Language :: Python :: 3.12
Classifier: Topic :: Software Development :: Libraries :: Python Modules
Classifier: Topic :: Terminals
Classifier: Topic :: Text Processing :: Markup
Classifier: Typing :: Typed
Requires-Python: >=3.8
License-File: LICENSE
Provides-Extra: dev
Requires-Dist: pytest>=7.0; extra == "dev"
Requires-Dist: pytest-asyncio>=0.21; extra == "dev"
Requires-Dist: black>=23.0; extra == "dev"
Requires-Dist: mypy>=1.0; extra == "dev"
Requires-Dist: ruff>=0.1.0; extra == "dev"
Dynamic: author
Dynamic: home-page
Dynamic: license-file
Dynamic: requires-python
